odm_report_shot_coverage/__init__.py
odm_report_shot_coverage/models/__init__.py
odm_report_shot_coverage/models/camera.py
odm_report_shot_coverage/models/point.py
odm_report_shot_coverage/models/reconstruction.py
odm_report_shot_coverage/models/shot.py
odm_report_shot_coverage/models/test_camera.py
odm_report_shot_coverage/models/test_fixtures.py
odm_report_shot_coverage/models/test_reconstruction.py
odm_report_shot_coverage/models/test_shot.py
odm_report_shot_coverage/models/test_wavefront_25d.py
odm_report_shot_coverage/models/wavefront_25d.py
odm_report_shot_coverage/scripts/__init__.py
odm_report_shot_coverage/scripts/report.py
odm_report_shot_coverage/scripts/web/index.css
odm_report_shot_coverage/scripts/web/index.html
odm_report_shot_coverage/scripts/web/index.js
odm_report_shot_coverage-0.1.4.dist-info/METADATA
odm_report_shot_coverage-0.1.4.dist-info/WHEEL
odm_report_shot_coverage-0.1.4.dist-info/entry_points.txt
odm_report_shot_coverage-0.1.4.dist-info/top_level.txt
odm_report_shot_coverage-0.1.4.dist-info/RECORD
