Metadata-Version: 2.1
Name: odm-report-shot-coverage
Version: 0.1.4
Summary: From an OpenDroneMap reconstruction, our goal is to see which part of the ortho photo is covered by each shot.
Home-page: https://github.com/terra-submersa/odm-report-shot-coverage
Author: Alexandre Masselot
Author-email: alexandre.masselot@gmail.com
License: UNKNOWN
Project-URL: Bug Tracker, https://github.com/terra-submersa/odm-report-shot-coverage/issues
Platform: UNKNOWN
Classifier: Programming Language :: Python :: 3
Classifier: License :: OSI Approved :: MIT License
Classifier: Operating System :: OS Independent
Requires-Python: >=3.8
Requires-Dist: geojson (>=2.5.0)
Requires-Dist: numpy (==1.22.3)
Requires-Dist: Pillow (>=9.1.0)
Requires-Dist: scipy
Requires-Dist: argparse
Requires-Dist: tqdm
